biokite/__init__.py
biokite/detector.py
biokite-0.1.0.dist-info/METADATA
biokite-0.1.0.dist-info/WHEEL
biokite-0.1.0.dist-info/top_level.txt
biokite-0.1.0.dist-info/RECORD
